{"type": "FeatureCollection", "features": [{"geometry": {"type": "Point", "coordinates": [25.3167, 54.6833]}, "type": "Feature", "properties": {"lang": "Yiddish", "year": "1924", "title": "\u1e7een di \u1e7fegn kraytsn zikh"}}, {"geometry": {"type": "Point", "coordinates": [28.9647, 41.0186]}, "type": "Feature", "properties": {"lang": "Turkish", "year": "2007", "title": "\u0130stikl\u00e2l Harbi"}}]}